vidl/__init__.py
vidl/config.py
vidl/default_user_md_parser.py
vidl/dl.py
vidl/md.py
vidl/run.py
vidl-4.4.0.dist-info/METADATA
vidl-4.4.0.dist-info/WHEEL
vidl-4.4.0.dist-info/entry_points.txt
vidl-4.4.0.dist-info/RECORD
