Metadata-Version: 2.3
Name: vidl
Version: 4.4.0
Summary: Downloads video/audio from anywhere, adding thumbnails and mp3 metadata if applicable
Keywords: youtube,download,video,audio,music
Author: kasper.space
Requires-Python: >=3.6,<4.0
Classifier: Programming Language :: Python :: 3
Classifier: Programming Language :: Python :: 3.6
Classifier: Programming Language :: Python :: 3.7
Classifier: Programming Language :: Python :: 3.8
Classifier: Programming Language :: Python :: 3.9
Classifier: Programming Language :: Python :: 3.10
Classifier: Programming Language :: Python :: 3.11
Classifier: Programming Language :: Python :: 3.12
Classifier: Programming Language :: Python :: 3.13
Requires-Dist: appdirs (>=1.4.4,<2.0.0)
Requires-Dist: colorboy (>=1.0.3,<2.0.0)
Requires-Dist: mutagen (>=1.45.1,<2.0.0)
Requires-Dist: yt-dlp (>2021.0.0)
Project-URL: Repository, https://github.com/probablykasper/vidl
